Metadata-Version: 1.1
Name: about
Version: 5.0.1
Summary: Software Metadata for Humans
Home-page: https://warehouse.python.org/project/about
Author: Sébastien Boisgérault
Author-email: Sebastien.Boisgerault@gmail.com
License: MIT License
Platform: UNKNOWN
Classifier: Operating System :: OS Independent
Classifier: Programming Language :: Python :: 2.7
Classifier: Topic :: Software Development
